localflavor/__init__.py
localflavor/deprecation.py
localflavor/ar/__init__.py
localflavor/ar/ar_provinces.py
localflavor/ar/forms.py
localflavor/at/__init__.py
localflavor/at/at_states.py
localflavor/at/forms.py
localflavor/au/__init__.py
localflavor/au/au_states.py
localflavor/au/forms.py
localflavor/au/models.py
localflavor/au/validators.py
localflavor/be/__init__.py
localflavor/be/be_provinces.py
localflavor/be/be_regions.py
localflavor/be/forms.py
localflavor/bg/__init__.py
localflavor/bg/models.py
localflavor/bg/utils.py
localflavor/bg/validators.py
localflavor/br/__init__.py
localflavor/br/br_states.py
localflavor/br/forms.py
localflavor/br/models.py
localflavor/br/validators.py
localflavor/by/__init__.py
localflavor/by/by_regions.py
localflavor/by/forms.py
localflavor/by/models.py
localflavor/by/validators.py
localflavor/ca/__init__.py
localflavor/ca/ca_provinces.py
localflavor/ca/forms.py
localflavor/ca/models.py
localflavor/ch/__init__.py
localflavor/ch/ch_states.py
localflavor/ch/forms.py
localflavor/cl/__init__.py
localflavor/cl/cl_regions.py
localflavor/cl/forms.py
localflavor/cn/__init__.py
localflavor/cn/cn_provinces.py
localflavor/cn/forms.py
localflavor/co/__init__.py
localflavor/co/co_departments.py
localflavor/co/forms.py
localflavor/cu/__init__.py
localflavor/cu/choices.py
localflavor/cu/forms.py
localflavor/cu/models.py
localflavor/cu/validators.py
localflavor/cz/__init__.py
localflavor/cz/cz_regions.py
localflavor/cz/forms.py
localflavor/de/__init__.py
localflavor/de/de_states.py
localflavor/de/forms.py
localflavor/dk/__init__.py
localflavor/dk/dk_municipalities.py
localflavor/dk/dk_postalcodes.py
localflavor/dk/forms.py
localflavor/ec/__init__.py
localflavor/ec/ec_provinces.py
localflavor/ec/forms.py
localflavor/ec/models.py
localflavor/ee/__init__.py
localflavor/ee/ee_counties.py
localflavor/ee/forms.py
localflavor/eg/__init__.py
localflavor/eg/choices.py
localflavor/eg/forms.py
localflavor/es/__init__.py
localflavor/es/es_provinces.py
django_localflavor-4.0.dist-info/LICENSE
django_localflavor-4.0.dist-info/METADATA
django_localflavor-4.0.dist-info/WHEEL
django_localflavor-4.0.dist-info/top_level.txt
django_localflavor-4.0.dist-info/RECORD
